collectfasta/__init__.py
collectfasta/py.typed
collectfasta/settings.py
collectfasta/management/__init__.py
collectfasta/management/commands/__init__.py
collectfasta/management/commands/collectstatic.py
collectfasta/strategies/__init__.py
collectfasta/strategies/azure.py
collectfasta/strategies/base.py
collectfasta/strategies/boto3.py
collectfasta/strategies/filesystem.py
collectfasta/strategies/gcloud.py
collectfasta/strategies/hashing.py
collectfasta/tests/__init__.py
collectfasta/tests/conftest.py
collectfasta/tests/settings.py
collectfasta/tests/test_settings.py
collectfasta/tests/utils.py
collectfasta/tests/command/__init__.py
collectfasta/tests/command/test_command.py
collectfasta/tests/command/test_disable.py
collectfasta/tests/command/test_post_process.py
collectfasta/tests/command/utils.py
collectfasta/tests/strategies/__init__.py
collectfasta/tests/strategies/test_caching_hash_strategy.py
collectfasta/tests/strategies/test_hash_strategy.py
collectfasta-3.3.3.dist-info/licenses/LICENSE
collectfasta-3.3.3.dist-info/METADATA
collectfasta-3.3.3.dist-info/WHEEL
collectfasta-3.3.3.dist-info/top_level.txt
collectfasta-3.3.3.dist-info/RECORD
