Metadata-Version: 2.4
Name: Collectfasta
Version: 3.3.3
Summary: A Faster Collectstatic
Home-page: https://github.com/jasongi/collectfasta/
Author: Anton Agestam, Jason Giancono
Author-email: jasongiancono+github@gmail.com
License: MIT License
Classifier: Environment :: Web Environment
Classifier: Intended Audience :: Developers
Classifier: Operating System :: OS Independent
Classifier: Programming Language :: Python
Classifier: Programming Language :: Python :: 3
Classifier: Programming Language :: Python :: 3.10
Classifier: Programming Language :: Python :: 3.11
Classifier: Programming Language :: Python :: 3.12
Classifier: Programming Language :: Python :: 3.13
Classifier: Programming Language :: Python :: 3.14
Classifier: Framework :: Django
Classifier: Framework :: Django :: 4.2
Classifier: Framework :: Django :: 5.2
Classifier: Framework :: Django :: 6.0
Requires-Python: >=3.10
License-File: LICENSE
Requires-Dist: Django>=4.2
Requires-Dist: django-storages>=1.13.2
Requires-Dist: typing-extensions
Dynamic: license-file
